{
  "schema_version": "GOLD_LEARNER_PROFILE_PERSISTED_V1",
  "engine_id": "VA_STELLA_GOLD_LIE_PROFILE_BUILDER",
  "engine_version": "1.4.3-standalone-no-imports",
  "created_at": "2026-07-11T18:06:39.008047+00:00",
  "student_id": "stress_weak",
  "latest_essay_id": "essay_weak_001",
  "latest_score": {
    "overall_band": 5.0,
    "criteria_bands": {
      "task_response": 5,
      "coherence_cohesion": 5,
      "lexical_resource": 5,
      "grammar": 5
    },
    "score_confidence": "normal",
    "score_status": "ready",
    "progress_tracking_allowed": true,
    "lie_update_allowed": true
  },
  "latest_error_profile": {
    "by_family": {
      "SUBJECT_VERB_AGREEMENT": 9,
      "SPELLING": 2,
      "COLLOCATION": 8,
      "NOUN_NUMBER_COUNTABILITY": 2
    },
    "by_capacity": {
      "sentence_control": 11,
      "lexical_precision": 10
    },
    "by_criterion": {
      "grammar": 11,
      "lexical_resource": 10
    },
    "total_chargeable": 21
  },
  "latest_priority_focus": [
    {
      "rank": 1,
      "capacity_domain": "sentence_control",
      "skill_tag": "sentence_control",
      "skill_id": "sentence_control",
      "student_label": "Sentence Control",
      "criterion": "grammar",
      "evidence_count": 11,
      "weighted_pressure": 11.0,
      "priority_level": "very_high",
      "top_families": [
        "SUBJECT_VERB_AGREEMENT",
        "NOUN_NUMBER_COUNTABILITY"
      ],
      "family_counts": {
        "SUBJECT_VERB_AGREEMENT": 9,
        "NOUN_NUMBER_COUNTABILITY": 2
      },
      "recommended_service": "writing_coach",
      "recommended_difficulty": "controlled",
      "priority_reason": "Selected from chargeable ErrorMap capacity evidence because downstream routing requires a stable skill focus.",
      "evidence_samples": [
        {
          "error_id": "row_676548d49a6838ac",
          "source_row_id": "row_676548d49a6838ac",
          "family": "SUBJECT_VERB_AGREEMENT",
          "surface_quote": "it compulsory",
          "sentence_index": 3,
          "severity": "moderate",
          "confidence": 0.95
        },
        {
          "error_id": "row_b247d87ede2f1fcd",
          "source_row_id": "row_b247d87ede2f1fcd",
          "family": "SUBJECT_VERB_AGREEMENT",
          "surface_quote": "many",
          "sentence_index": 2,
          "severity": "moderate",
          "confidence": 0.78
        },
        {
          "error_id": "row_c2d7794db51021c4",
          "source_row_id": "row_c2d7794db51021c4",
          "family": "SUBJECT_VERB_AGREEMENT",
          "surface_quote": "think",
          "sentence_index": 2,
          "severity": "moderate",
          "confidence": 0.78
        },
        {
          "error_id": "row_c09ddb5b7942644a",
          "source_row_id": "row_c09ddb5b7942644a",
          "family": "SUBJECT_VERB_AGREEMENT",
          "surface_quote": "they meets",
          "sentence_index": 4,
          "severity": "moderate",
          "confidence": 0.72
        },
        {
          "error_id": "row_ac22dbde7aae5a47",
          "source_row_id": "row_ac22dbde7aae5a47",
          "family": "SUBJECT_VERB_AGREEMENT",
          "surface_quote": "students will learns",
          "sentence_index": 3,
          "severity": "moderate",
          "confidence": 0.72
        }
      ]
    },
    {
      "rank": 2,
      "capacity_domain": "lexical_precision",
      "skill_tag": "lexical_precision",
      "skill_id": "lexical_precision",
      "student_label": "Lexical Precision",
      "criterion": "lexical_resource",
      "evidence_count": 10,
      "weighted_pressure": 10.0,
      "priority_level": "very_high",
      "top_families": [
        "COLLOCATION",
        "SPELLING"
      ],
      "family_counts": {
        "COLLOCATION": 8,
        "SPELLING": 2
      },
      "recommended_service": "lret",
      "recommended_difficulty": "controlled",
      "priority_reason": "Selected from chargeable ErrorMap capacity evidence because downstream routing requires a stable skill focus.",
      "evidence_samples": [
        {
          "error_id": "row_74ca7a2759e6c7d3",
          "source_row_id": "row_74ca7a2759e6c7d3",
          "family": "SPELLING",
          "surface_quote": "dont",
          "sentence_index": 2,
          "severity": "moderate",
          "confidence": 0.86
        },
        {
          "error_id": "row_b10b868020e0a09c",
          "source_row_id": "row_b10b868020e0a09c",
          "family": "SPELLING",
          "surface_quote": "dont",
          "sentence_index": 11,
          "severity": "moderate",
          "confidence": 0.86
        },
        {
          "error_id": "row_60d44c8a2d1d75d7",
          "source_row_id": "row_60d44c8a2d1d75d7",
          "family": "COLLOCATION",
          "surface_quote": "doing community service",
          "sentence_index": 4,
          "severity": "moderate",
          "confidence": 0.85
        },
        {
          "error_id": "row_d5ae6b0f75212904",
          "source_row_id": "row_d5ae6b0f75212904",
          "family": "COLLOCATION",
          "surface_quote": "old peoples",
          "sentence_index": 4,
          "severity": "moderate",
          "confidence": 0.9
        },
        {
          "error_id": "row_11d08edcd0ccf341",
          "source_row_id": "row_11d08edcd0ccf341",
          "family": "COLLOCATION",
          "surface_quote": "homeless peoples",
          "sentence_index": 4,
          "severity": "moderate",
          "confidence": 0.9
        }
      ]
    }
  ],
  "service_artifact_status": {
    "feedback": {
      "available": true,
      "schema_version": "FEEDBACK_REPORT_V6C_CLI_STANDALONE",
      "engine_id": "VA_STELLA_FEEDBACK_ENGINE_V6C_CLI"
    },
    "evaluator": {
      "available": true,
      "schema_version": "WKM_OUTPUT_V8.3",
      "engine_id": null
    },
    "lret": {
      "available": true,
      "schema_version": "LRET_OUTPUT_V1.5",
      "engine_id": null
    },
    "writing_coach": {
      "available": true,
      "schema_version": "WRITING_COACH_OUTPUT_V1_2_10_PROACTIVE_ADAPTIVE_CLI",
      "engine_id": null
    },
    "practice": {
      "available": true,
      "schema_version": "GOLD_PRACTICE_SESSION_ADAPTIVE_V1",
      "engine_id": "VA_STELLA_GOLD_PRACTICE_ENGINE_BRIDGE"
    }
  },
  "next_best_action": {
    "capacity_domain": "sentence_control",
    "skill_tag": "sentence_control",
    "recommended_service": "writing_coach",
    "source": "directive"
  },
  "learning_state": {
    "profile_update_allowed": true,
    "trend_update_allowed": true,
    "mastery_update_policy": "evidence_accumulation_only_until_student_attempts_practice_or_coach_tasks"
  },
  "boundary": "LIE profile aggregates completed Gold artifacts only; no scoring, detection, feedback generation, or exercise generation is performed here.",
  "_persist": {
    "engine_id": "VA_STELLA_GOLD_PROFILE_PERSIST",
    "engine_version": "1.0.0-standalone-no-imports",
    "persisted_at": "2026-07-11T18:06:39.398258+00:00",
    "lie_update_allowed": true,
    "action": "profile_advanced"
  },
  "_continuity": {
    "sessions_analyzed": 1,
    "last_session_id": "gold_20260711_195357_essay_weak_001_8d9dbaa3",
    "last_updated_at": "2026-07-11T18:06:39.398258+00:00",
    "previous_directive_snapshot": {
      "schema_version": "DIRECTIVE_ADAPTER_STANDALONE_V1_4_3",
      "engine_id": "VA_STELLA_DIRECTIVE_ADAPTER_CLI",
      "engine_version": "1.4.3-standalone-no-imports",
      "created_at": "2026-07-11T17:57:44.311856+00:00",
      "boundary": "Directive adapter converts upstream priority and score contract into routing metadata only.",
      "source_priority_schema": "PRIORITY_NORMALIZED_V1_4_3",
      "focus_source": "priority_normalized",
      "focus_areas": [
        {
          "rank": 1,
          "capacity_domain": "sentence_control",
          "skill_tag": "sentence_control",
          "skill_id": "sentence_control",
          "student_label": "Sentence Control",
          "criterion": "grammar",
          "evidence_count": 11,
          "weighted_pressure": 11.0,
          "priority_level": "very_high",
          "top_families": [
            "SUBJECT_VERB_AGREEMENT",
            "NOUN_NUMBER_COUNTABILITY"
          ],
          "family_counts": {
            "SUBJECT_VERB_AGREEMENT": 9,
            "NOUN_NUMBER_COUNTABILITY": 2
          },
          "recommended_service": "writing_coach",
          "recommended_difficulty": "controlled",
          "priority_reason": "Selected from chargeable ErrorMap capacity evidence because downstream routing requires a stable skill focus.",
          "evidence_samples": [
            {
              "error_id": "row_676548d49a6838ac",
              "source_row_id": "row_676548d49a6838ac",
              "family": "SUBJECT_VERB_AGREEMENT",
              "surface_quote": "it compulsory",
              "sentence_index": 3,
              "severity": "moderate",
              "confidence": 0.95
            },
            {
              "error_id": "row_b247d87ede2f1fcd",
              "source_row_id": "row_b247d87ede2f1fcd",
              "family": "SUBJECT_VERB_AGREEMENT",
              "surface_quote": "many",
              "sentence_index": 2,
              "severity": "moderate",
              "confidence": 0.78
            },
            {
              "error_id": "row_c2d7794db51021c4",
              "source_row_id": "row_c2d7794db51021c4",
              "family": "SUBJECT_VERB_AGREEMENT",
              "surface_quote": "think",
              "sentence_index": 2,
              "severity": "moderate",
              "confidence": 0.78
            },
            {
              "error_id": "row_c09ddb5b7942644a",
              "source_row_id": "row_c09ddb5b7942644a",
              "family": "SUBJECT_VERB_AGREEMENT",
              "surface_quote": "they meets",
              "sentence_index": 4,
              "severity": "moderate",
              "confidence": 0.72
            },
            {
              "error_id": "row_ac22dbde7aae5a47",
              "source_row_id": "row_ac22dbde7aae5a47",
              "family": "SUBJECT_VERB_AGREEMENT",
              "surface_quote": "students will learns",
              "sentence_index": 3,
              "severity": "moderate",
              "confidence": 0.72
            }
          ]
        },
        {
          "rank": 2,
          "capacity_domain": "lexical_precision",
          "skill_tag": "lexical_precision",
          "skill_id": "lexical_precision",
          "student_label": "Lexical Precision",
          "criterion": "lexical_resource",
          "evidence_count": 10,
          "weighted_pressure": 10.0,
          "priority_level": "very_high",
          "top_families": [
            "COLLOCATION",
            "SPELLING"
          ],
          "family_counts": {
            "COLLOCATION": 8,
            "SPELLING": 2
          },
          "recommended_service": "lret",
          "recommended_difficulty": "controlled",
          "priority_reason": "Selected from chargeable ErrorMap capacity evidence because downstream routing requires a stable skill focus.",
          "evidence_samples": [
            {
              "error_id": "row_74ca7a2759e6c7d3",
              "source_row_id": "row_74ca7a2759e6c7d3",
              "family": "SPELLING",
              "surface_quote": "dont",
              "sentence_index": 2,
              "severity": "moderate",
              "confidence": 0.86
            },
            {
              "error_id": "row_b10b868020e0a09c",
              "source_row_id": "row_b10b868020e0a09c",
              "family": "SPELLING",
              "surface_quote": "dont",
              "sentence_index": 11,
              "severity": "moderate",
              "confidence": 0.86
            },
            {
              "error_id": "row_60d44c8a2d1d75d7",
              "source_row_id": "row_60d44c8a2d1d75d7",
              "family": "COLLOCATION",
              "surface_quote": "doing community service",
              "sentence_index": 4,
              "severity": "moderate",
              "confidence": 0.85
            },
            {
              "error_id": "row_d5ae6b0f75212904",
              "source_row_id": "row_d5ae6b0f75212904",
              "family": "COLLOCATION",
              "surface_quote": "old peoples",
              "sentence_index": 4,
              "severity": "moderate",
              "confidence": 0.9
            },
            {
              "error_id": "row_11d08edcd0ccf341",
              "source_row_id": "row_11d08edcd0ccf341",
              "family": "COLLOCATION",
              "surface_quote": "homeless peoples",
              "sentence_index": 4,
              "severity": "moderate",
              "confidence": 0.9
            }
          ]
        }
      ],
      "primary_focus": {
        "rank": 1,
        "capacity_domain": "sentence_control",
        "skill_tag": "sentence_control",
        "skill_id": "sentence_control",
        "student_label": "Sentence Control",
        "criterion": "grammar",
        "evidence_count": 11,
        "weighted_pressure": 11.0,
        "priority_level": "very_high",
        "top_families": [
          "SUBJECT_VERB_AGREEMENT",
          "NOUN_NUMBER_COUNTABILITY"
        ],
        "family_counts": {
          "SUBJECT_VERB_AGREEMENT": 9,
          "NOUN_NUMBER_COUNTABILITY": 2
        },
        "recommended_service": "writing_coach",
        "recommended_difficulty": "controlled",
        "priority_reason": "Selected from chargeable ErrorMap capacity evidence because downstream routing requires a stable skill focus.",
        "evidence_samples": [
          {
            "error_id": "row_676548d49a6838ac",
            "source_row_id": "row_676548d49a6838ac",
            "family": "SUBJECT_VERB_AGREEMENT",
            "surface_quote": "it compulsory",
            "sentence_index": 3,
            "severity": "moderate",
            "confidence": 0.95
          },
          {
            "error_id": "row_b247d87ede2f1fcd",
            "source_row_id": "row_b247d87ede2f1fcd",
            "family": "SUBJECT_VERB_AGREEMENT",
            "surface_quote": "many",
            "sentence_index": 2,
            "severity": "moderate",
            "confidence": 0.78
          },
          {
            "error_id": "row_c2d7794db51021c4",
            "source_row_id": "row_c2d7794db51021c4",
            "family": "SUBJECT_VERB_AGREEMENT",
            "surface_quote": "think",
            "sentence_index": 2,
            "severity": "moderate",
            "confidence": 0.78
          },
          {
            "error_id": "row_c09ddb5b7942644a",
            "source_row_id": "row_c09ddb5b7942644a",
            "family": "SUBJECT_VERB_AGREEMENT",
            "surface_quote": "they meets",
            "sentence_index": 4,
            "severity": "moderate",
            "confidence": 0.72
          },
          {
            "error_id": "row_ac22dbde7aae5a47",
            "source_row_id": "row_ac22dbde7aae5a47",
            "family": "SUBJECT_VERB_AGREEMENT",
            "surface_quote": "students will learns",
            "sentence_index": 3,
            "severity": "moderate",
            "confidence": 0.72
          }
        ]
      },
      "score_context": {
        "released_score": {
          "overall_band": 5.0,
          "criteria_bands": {
            "task_response": 5,
            "coherence_cohesion": 5,
            "lexical_resource": 5,
            "grammar": 5
          },
          "score_family": "B1_WEAK",
          "score_released": true
        },
        "score_confidence": "normal",
        "score_status": "ready",
        "verifier_status": "pass",
        "adjudication_status": "confirmed",
        "progress_tracking_allowed": true,
        "lie_update_allowed": true
      },
      "score_confidence": "normal",
      "adjudication_status": "confirmed",
      "progress_tracking_allowed": true,
      "gold_learning_directive": {
        "next_best_skill": "sentence_control",
        "next_best_capacity_domain": "sentence_control",
        "recommended_service": "writing_coach",
        "learning_update_allowed": true,
        "mastery_update_allowed": false,
        "recommended_difficulty": "controlled",
        "reason": "Selected from chargeable ErrorMap capacity evidence because downstream routing requires a stable skill focus."
      },
      "learner_profile_context": {
        "profile_supplied": true,
        "profile_version": "GOLD_PRIOR_CONTEXT_V1"
      },
      "quality_flags": {
        "has_primary_focus": true,
        "has_recommended_service": true
      }
    }
  }
}
